Metadata-Version: 1.0
Name: test4pypi
Version: 0.0.1
Summary: just a test 4 pypi
Home-page: https://github.com/zsdlove/hades
Author: pony
Author-email: 747289639@qq.com
License: MIT License
Keywords: test4pypi
Platform: any
